agentkernel/__init__.py
agentkernel/adk.py
agentkernel/api/__init__.py
agentkernel/api/a2a/__init__.py
agentkernel/api/a2a/a2a.py
agentkernel/api/a2a/handler.py
agentkernel/api/handler.py
agentkernel/api/http.py
agentkernel/api/mcp/__init__.py
agentkernel/api/mcp/akmcp.py
agentkernel/aws.py
agentkernel/cli/__init__.py
agentkernel/cli/cli.py
agentkernel/core/__init__.py
agentkernel/core/base.py
agentkernel/core/builder.py
agentkernel/core/config.py
agentkernel/core/hooks.py
agentkernel/core/model.py
agentkernel/core/module.py
agentkernel/core/runtime.py
agentkernel/core/service.py
agentkernel/core/session/__init__.py
agentkernel/core/session/base.py
agentkernel/core/session/dynamodb.py
agentkernel/core/session/in_memory.py
agentkernel/core/session/redis.py
agentkernel/core/session/serde.py
agentkernel/core/util/config_yaml_util.py
agentkernel/core/util/key_value_cache.py
agentkernel/crewai.py
agentkernel/deployment/__init__.py
agentkernel/deployment/aws/__init__.py
agentkernel/deployment/aws/aklambda.py
agentkernel/framework/__init__.py
agentkernel/framework/adk/__init__.py
agentkernel/framework/adk/adk.py
agentkernel/framework/crewai/__init__.py
agentkernel/framework/crewai/crewai.py
agentkernel/framework/langgraph/__init__.py
agentkernel/framework/langgraph/langgraph.py
agentkernel/framework/openai/__init__.py
agentkernel/framework/openai/openai.py
agentkernel/gmail.py
agentkernel/guardrail/__init__.py
agentkernel/guardrail/bedrock.py
agentkernel/guardrail/guardrail.py
agentkernel/guardrail/openai.py
agentkernel/instagram.py
agentkernel/integration/__init__.py
agentkernel/integration/gmail/README.md
agentkernel/integration/gmail/__init__.py
agentkernel/integration/gmail/gmail_chat.py
agentkernel/integration/instagram/README.md
agentkernel/integration/instagram/__init__.py
agentkernel/integration/instagram/instagram_chat.py
agentkernel/integration/messenger/README.md
agentkernel/integration/messenger/__init__.py
agentkernel/integration/messenger/messenger_chat.py
agentkernel-0.2.11.dist-info/WHEEL
agentkernel-0.2.11.dist-info/METADATA
agentkernel-0.2.11.dist-info/RECORD
