Metadata-Version: 2.3
Name: agentkernel
Version: 0.2.11
Summary: Agent Kernel - Unified AI Agents Runtime
Author: Yaala Labs
Author-email: Yaala Labs <agentkernel@yaalalabs.com>
License: MIT
Requires-Dist: deprecated>=1.3.1
Requires-Dist: pydantic>=2.11.7
Requires-Dist: pydantic-settings>=2.10.1
Requires-Dist: pyyaml>=6.0.2
Requires-Dist: singleton-type>=0.0.5
Requires-Dist: a2a-sdk[http-server]>=0.3.6 ; extra == 'a2a'
Requires-Dist: google-adk>=1.14.1 ; extra == 'adk'
Requires-Dist: litellm~=1.74.3 ; extra == 'adk'
Requires-Dist: openinference-instrumentation-google-adk>=0.1.6 ; extra == 'adk'
Requires-Dist: fastapi>=0.118.0 ; extra == 'api'
Requires-Dist: uvicorn>=0.37.0 ; extra == 'api'
Requires-Dist: gunicorn>=23.0.0 ; extra == 'api'
Requires-Dist: boto3>=1.41.4 ; extra == 'aws'
Requires-Dist: crewai>=0.150.0 ; extra == 'crewai'
Requires-Dist: openinference-instrumentation-crewai>=0.1.16 ; extra == 'crewai'
Requires-Dist: openinference-instrumentation-litellm>=0.1.28 ; extra == 'crewai'
Requires-Dist: google-auth>=2.0.0 ; extra == 'gmail'
Requires-Dist: google-auth-oauthlib>=1.0.0 ; extra == 'gmail'
Requires-Dist: google-auth-httplib2>=0.2.0 ; extra == 'gmail'
Requires-Dist: google-api-python-client>=2.0.0 ; extra == 'gmail'
Requires-Dist: httpx>=0.27.0 ; extra == 'instagram'
Requires-Dist: langfuse>=3.9.2 ; extra == 'langfuse'
Requires-Dist: nest-asyncio>=1.6.0 ; extra == 'langfuse'
Requires-Dist: langgraph~=1.0.5 ; extra == 'langgraph'
Requires-Dist: langchain~=1.2.3 ; extra == 'langgraph'
Requires-Dist: langchain-community~=0.4.1 ; extra == 'langgraph'
Requires-Dist: litellm~=1.74.9 ; extra == 'langgraph'
Requires-Dist: fastmcp>=2.12.4 ; extra == 'mcp'
Requires-Dist: httpx>=0.27.0 ; extra == 'messenger'
Requires-Dist: openai-agents>=0.6.5 ; extra == 'openai'
Requires-Dist: openinference-instrumentation-openai-agents>=1.4.0 ; extra == 'openai'
Requires-Dist: openai-guardrails>=0.2.1 ; extra == 'openai'
Requires-Dist: traceloop-sdk>=0.48.0 ; extra == 'openllmetry'
Requires-Dist: redis>=7.1.0 ; extra == 'redis'
Requires-Dist: slack-bolt==1.22.0 ; extra == 'slack'
Requires-Dist: httpx>=0.27.0 ; extra == 'slack'
Requires-Dist: httpx>=0.27.0 ; extra == 'telegram'
Requires-Dist: pytest>=8.4.1 ; extra == 'test'
Requires-Dist: pytest-asyncio>=1.2.0 ; extra == 'test'
Requires-Dist: pytest-cov>=6.2.1 ; extra == 'test'
Requires-Dist: pytest-html>=4.1.1 ; extra == 'test'
Requires-Dist: pytest-order>=1.3.0 ; extra == 'test'
Requires-Dist: rapidfuzz>=3.14.1 ; extra == 'test'
Requires-Dist: ragas>=0.4.1 ; extra == 'test'
Requires-Dist: datasets>=2.14.0 ; extra == 'test'
Requires-Dist: pandas>=2.0.0 ; extra == 'test'
Requires-Dist: litellm>=1.74.9 ; extra == 'test'
Requires-Dist: httpx>=0.27.0 ; extra == 'whatsapp'
Requires-Python: >=3.12, <3.14
Provides-Extra: a2a
Provides-Extra: adk
Provides-Extra: api
Provides-Extra: aws
Provides-Extra: cli
Provides-Extra: crewai
Provides-Extra: gmail
Provides-Extra: instagram
Provides-Extra: langfuse
Provides-Extra: langgraph
Provides-Extra: mcp
Provides-Extra: messenger
Provides-Extra: openai
Provides-Extra: openllmetry
Provides-Extra: redis
Provides-Extra: slack
Provides-Extra: telegram
Provides-Extra: test
Provides-Extra: whatsapp
